debtcollector/__init__.py
debtcollector/_utils.py
debtcollector/moves.py
debtcollector/removals.py
debtcollector/renames.py
debtcollector/updating.py
debtcollector/fixtures/__init__.py
debtcollector/fixtures/disable.py
debtcollector/tests/__init__.py
debtcollector/tests/base.py
debtcollector/tests/test_deprecation.py
debtcollector-3.0.0.dist-info/AUTHORS
debtcollector-3.0.0.dist-info/LICENSE
debtcollector-3.0.0.dist-info/METADATA
debtcollector-3.0.0.dist-info/WHEEL
debtcollector-3.0.0.dist-info/pbr.json
debtcollector-3.0.0.dist-info/top_level.txt
debtcollector-3.0.0.dist-info/RECORD
